dlhub_sdk/__init__.py
dlhub_sdk/client.py
dlhub_sdk/config.py
dlhub_sdk/version.py
dlhub_sdk/models/__init__.py
dlhub_sdk/models/datacite.py
dlhub_sdk/models/servables/__init__.py
dlhub_sdk/models/servables/keras.py
dlhub_sdk/models/servables/python.py
dlhub_sdk/models/servables/pytorch.py
dlhub_sdk/models/servables/sklearn.py
dlhub_sdk/models/servables/tensorflow.py
dlhub_sdk/utils/__init__.py
dlhub_sdk/utils/files.py
dlhub_sdk/utils/funcx_login_manager.py
dlhub_sdk/utils/futures.py
dlhub_sdk/utils/inspect.py
dlhub_sdk/utils/publish.py
dlhub_sdk/utils/schemas.py
dlhub_sdk/utils/search.py
dlhub_sdk/utils/types.py
dlhub_sdk/utils/validation.py
dlhub_sdk-2.1.0.dist-info/LICENSE
dlhub_sdk-2.1.0.dist-info/METADATA
dlhub_sdk-2.1.0.dist-info/WHEEL
dlhub_sdk-2.1.0.dist-info/top_level.txt
dlhub_sdk-2.1.0.dist-info/RECORD
