Metadata-Version: 2.1
Name: dlhub-sdk
Version: 2.1.0
Summary: Python interface and utilities for DLHub
Home-page: https://github.com/DLHub-Argonne/dlhub_sdk
Author: Ben Blaiszik
Author-email: bblaiszik@anl.gov
License: Apache License, Version 2.0
Keywords: DLHub,Data and Learning Hub for Science,machine learning,data publication,reproducibility
Classifier: Development Status :: 3 - Alpha
Classifier: Intended Audience :: Science/Research
Classifier: License :: OSI Approved :: Apache Software License
Classifier: Natural Language :: English
Classifier: Operating System :: OS Independent
Classifier: Programming Language :: Python :: 3
Classifier: Topic :: Scientific/Engineering
Requires-Python: >=3.4
License-File: LICENSE
Requires-Dist: globus-sdk (<4,>=3)
Requires-Dist: requests (>=2.24.0)
Requires-Dist: mdf-toolbox (>=0.5.4)
Requires-Dist: jsonschema (>=3.2.0)
Requires-Dist: globus-compute-sdk (>=2.0.0)
Requires-Dist: pydantic
Requires-Dist: numpy
Requires-Dist: PyGithub
